pygame_shaders_setup/__init__.py
pygame_shaders_setup/pygame_shaders.py
pygame_shaders_setup/screen_rect.py
pygame_shaders_setup/shader_setup.py
pygame_shaders_setup/texture.py
pygame_shaders_setup-0.0.7.dist-info/METADATA
pygame_shaders_setup-0.0.7.dist-info/WHEEL
pygame_shaders_setup-0.0.7.dist-info/top_level.txt
pygame_shaders_setup-0.0.7.dist-info/RECORD
